sensamag_utility/__init__.py
sensamag_utility/__main__.py
sensamag_utility/connection_manager.py
sensamag_utility/csv_reader.py
sensamag_utility/csv_schema.py
sensamag_utility/drop_table.py
sensamag_utility/exporter.py
sensamag_utility/importer.py
sensamag_utility/language.py
sensamag_utility/main.py
sensamag_utility/utility.py
sensamag-1.0.3.dist-info/METADATA
sensamag-1.0.3.dist-info/WHEEL
sensamag-1.0.3.dist-info/entry_points.txt
sensamag-1.0.3.dist-info/top_level.txt
sensamag-1.0.3.dist-info/zip-safe
sensamag-1.0.3.dist-info/RECORD
