Metadata-Version: 2.1
Name: sensamag
Version: 1.0.3
Summary: Utility library for sensamag data base
Home-page: https://github.com/freezerain/sensamag-utility
Author-email: "rain-ilia@rambler.ru"
Requires-Dist: typer[all]
Requires-Dist: rich
Requires-Dist: mariadb
Provides-Extra: dev
Requires-Dist: black ; extra == 'dev'
Provides-Extra: notebook
Requires-Dist: jupyter ; extra == 'notebook'
